nssm_exe/__init__.py
nssm_exe/nssm.exe
nssm_exe-2.24.post101.data/data/Scripts/nssm.exe
nssm_exe-2.24.post101.dist-info/METADATA
nssm_exe-2.24.post101.dist-info/WHEEL
nssm_exe-2.24.post101.dist-info/RECORD
