Metadata-Version: 2.4
Name: nssm_exe
Version: 2.24.post101
Summary: Bundles nssm.exe (Non-Sucking Service Manager) and installs the executable into the Python Scripts directory for Windows (provides a portable nssm.exe when the package is installed).
Requires-Python: >=3.13
